svmloader.so
svmloader-0.4.dist-info/top_level.txt
svmloader-0.4.dist-info/metadata.json
svmloader-0.4.dist-info/WHEEL
svmloader-0.4.dist-info/METADATA
svmloader-0.4.dist-info/DESCRIPTION.rst
svmloader-0.4.dist-info/RECORD
